jeckin/__init__.py
jeckin/main.py
jeckin/template-config.ini
jeckin/utils.py
jeckin/socks/SocksProxy.py
jeckin/socks/__init__.py
jeckin/tunnel/__init__.py
jeckin/tunnel/handler/__init__.py
jeckin/tunnel/handler/base_tunnel_handler.py
jeckin/tunnel/handler/base_tunnel_proxy_handler.py
jeckin/tunnel/handler/base_tunnel_ssl_tls_handler.py
jeckin/tunnel/handler/direct_ssh_handler.py
jeckin/tunnel/handler/direct_ssltls_ssh_handler.py
jeckin/tunnel/handler/proxy_ssh_handler.py
jeckin/tunnel/handler/proxy_ssltls_ssh_handler.py
jeckin/tunnel/ssh_client/__init__.py
jeckin/tunnel/ssh_client/ssh_client_native.py
jeckin/tunnel/ssh_client/ssh_client_paramiko.py
jeckin-0.0.2.dist-info/METADATA
jeckin-0.0.2.dist-info/WHEEL
jeckin-0.0.2.dist-info/entry_points.txt
jeckin-0.0.2.dist-info/top_level.txt
jeckin-0.0.2.dist-info/RECORD
