Metadata-Version: 2.1
Name: jeckin
Version: 0.0.2
Summary: SSH HTTP Injector
Author: Restu Suhendar
Author-email: restu.suhendar@gmail.com
Project-URL: Source, https://github.com/aarestu/jeckin
Project-URL: Issues, https://github.com/aarestu/jeckin/issues
Keywords: python,ssh,injector,free internet,tunneling,internet gratis,http injector
Classifier: Development Status :: 1 - Planning
Classifier: Intended Audience :: Developers
Classifier: Programming Language :: Python :: 3
Classifier: Operating System :: Unix
Classifier: Operating System :: MacOS :: MacOS X
Classifier: Operating System :: Microsoft :: Windows
Requires-Python: >=3.7, <4
Requires-Dist: paramiko (>=2.4)
